sqlatypemodel/__init__.py
sqlatypemodel/exceptions.py
sqlatypemodel/mixin/__init__.py
sqlatypemodel/mixin/_introspection_data.py
sqlatypemodel/mixin/events.py
sqlatypemodel/mixin/inspection.py
sqlatypemodel/mixin/mixin.py
sqlatypemodel/mixin/protocols.py
sqlatypemodel/mixin/serialization.py
sqlatypemodel/mixin/state.py
sqlatypemodel/mixin/types.py
sqlatypemodel/mixin/wrapping.py
sqlatypemodel/model_type/__init__.py
sqlatypemodel/model_type/model_type.py
sqlatypemodel/model_type/protocols.py
sqlatypemodel/py.typed
sqlatypemodel/util/__init__.py
sqlatypemodel/util/_sentinel.py
sqlatypemodel/util/attrs.py
sqlatypemodel/util/constants.py
sqlatypemodel/util/dataclasses.py
sqlatypemodel/util/json.py
sqlatypemodel/util/sqlalchemy.py
sqlatypemodel-0.8.4.dist-info/METADATA
sqlatypemodel-0.8.4.dist-info/WHEEL
sqlatypemodel-0.8.4.dist-info/licenses/LICENSE
sqlatypemodel-0.8.4.dist-info/RECORD
