Metadata-Version: 2.4
Name: sqlatypemodel
Version: 0.8.4
Summary: Typed JSON fields for SQLAlchemy with automatic mutation tracking
License: MIT
License-File: LICENSE
Author: grehban
Author-email: maximfeedback19@gmail.com
Requires-Python: >=3.10
Classifier: Development Status :: 4 - Beta
Classifier: Intended Audience :: Developers
Classifier: Programming Language :: Python :: 3
Classifier: Programming Language :: Python :: 3.10
Classifier: Programming Language :: Python :: 3.11
Classifier: Programming Language :: Python :: 3.12
Classifier: Programming Language :: Python :: 3.13
Classifier: Programming Language :: Python :: 3.14
Classifier: Framework :: Pydantic
Classifier: Framework :: Pydantic :: 2
Classifier: Typing :: Typed
Provides-Extra: docs
Provides-Extra: fast
Requires-Dist: Sphinx (>=8.0.2,<9.0.0) ; extra == "docs"
Requires-Dist: Sphinx-Substitution-Extensions (>=2024.8.6) ; extra == "docs"
Requires-Dist: attrs (>=23.0.0) ; extra == "docs"
Requires-Dist: furo (>=2024.8.6) ; extra == "docs"
Requires-Dist: markdown-include (>=0.8.1) ; extra == "docs"
Requires-Dist: orjson (>=3.11.5) ; extra == "docs"
Requires-Dist: orjson (>=3.11.5.0,<4.0.0) ; extra == "fast"
Requires-Dist: pre-commit (>=4.5.1,<5.0.0)
Requires-Dist: pydantic (>=2.0.0) ; extra == "docs"
Requires-Dist: pygments (>=2.18.0) ; extra == "docs"
Requires-Dist: pymdown-extensions (>=10.3) ; extra == "docs"
Requires-Dist: sphinx-autobuild (>=2024.9.3) ; extra == "docs"
Requires-Dist: sphinx-copybutton (>=0.5.2) ; extra == "docs"
Requires-Dist: sphinx-intl (>=2.2.0,<3.0.0) ; extra == "docs"
Requires-Dist: sphinxcontrib-towncrier (>=0.4.0a0) ; extra == "docs"
Requires-Dist: sqlalchemy (>=2.0.0,<3.0.0)
Requires-Dist: towncrier (>=24.8.0) ; extra == "docs"
Project-URL: Documentation, https://github.com/GrehBan/sqlatypemodel/
Project-URL: Homepage, https://github.com/GrehBan/sqlatypemodel/
Project-URL: Repository, https://github.com/GrehBan/sqlatypemodel/
